MANIFEST.in
README.md
setup.cfg
setup.py
bin/mTree_control
mTree/__init__.py
mTree.egg-info/PKG-INFO
mTree.egg-info/SOURCES.txt
mTree.egg-info/dependency_links.txt
mTree.egg-info/requires.txt
mTree.egg-info/top_level.txt
mTree/base/__init__.py
mTree/base/admin.py
mTree/base/environment.py
mTree/base/institution.py
mTree/base/mes_period.py
mTree/base/mes_player.py
mTree/base/period.py
mTree/base/player.py
mTree/base/player_controller.py
mTree/base/recorder.py
mTree/base/response.py
mTree/base/server.py
mTree/base/session.py
mTree/base/subject.py
mTree/base/user.py
mTree/base/views.py
mTree/base/admin_templates/admin.js
mTree/base/admin_templates/admin_base.html
mTree/base/admin_templates/component_view.html
mTree/base/agents/__init__.py
mTree/base/agents/sequential_agent_controller.py
mTree/base/agents/simultaneous_agent_controller.py
mTree/base/user_templates/old_search.html
mTree/base/user_templates/subject.js
mTree/base/user_templates/subject_base.html
mTree/base/user_templates/wait_screen.html
mTree/components/__init__.py
mTree/components/admin_message.py
mTree/components/admin_response.py
mTree/components/registry.py
mTree/experiment/__init__.py
mTree/experiment/agent_experiment.py
mTree/experiment/basic_experiment.py
mTree/microeconomic_system/__init__.py
mTree/microeconomic_system/agent.py
mTree/microeconomic_system/agent_pool.py
mTree/microeconomic_system/container.py
mTree/microeconomic_system/directive_decorators.py
mTree/microeconomic_system/environment.py
mTree/microeconomic_system/institution.py
mTree/microeconomic_system/logging.py
mTree/microeconomic_system/message.py
mTree/microeconomic_system/message_space.py
mTree/microeconomic_system/multi_container.py
mTree/microeconomic_system/subject_container.py
mTree/microeconomic_system/universe.py
mTree/new_objects/__init__.py
mTree/new_objects/experiment.py
mTree/new_objects/treatments.py
mTree/new_objects/user_state.py
mTree/server/__init__.py
mTree/server/admin.py
mTree/server/server.py
mTree/system/__init__.py
mTree/system/package_loader.py
mTree/templates/__init__.py