Metadata-Version: 1.0
Name: mTree
Version: 0.3b12
Summary: This is the base mTree package
Home-page: https://github.com/gmucsn/mTree
Author: GMU CSN
Author-email: mtree.email@gmail.com
License: MIT
Keywords: computational experimental economics
Platform: UNKNOWN
